jsonllm_client/__init__.py
jsonllm_client/client.py
jsonllm_client/extraction_request.py
jsonllm_client/request_status.py
jsonllm_client/submit_request_result.py
jsonllm_client/utils.py
jsonllm_client-0.16.0.dist-info/licenses/LICENSE
jsonllm_client-0.16.0.dist-info/METADATA
jsonllm_client-0.16.0.dist-info/WHEEL
jsonllm_client-0.16.0.dist-info/top_level.txt
jsonllm_client-0.16.0.dist-info/RECORD
