Metadata-Version: 2.4
Name: jsonllm-client
Version: 0.16.0
Summary: Client for JsonLLM API
Author-email: LocalTransformer team <info@localtransformer.com>
License: MIT License
Project-URL: Homepage, https://github.com/microlib-org/jsonllm-client
Classifier: License :: OSI Approved :: MIT License
Classifier: Programming Language :: Python
Classifier: Programming Language :: Python :: 3
Requires-Python: >=3.8
License-File: LICENSE
Requires-Dist: requests
Requires-Dist: tqdm
Requires-Dist: pydantic
Provides-Extra: dev
Requires-Dist: pytest; extra == "dev"
Dynamic: license-file
